<?xml version="1.0" encoding="utf-8" ?>
<c2eventsheet>
    <!--All the 'name' attributes are ignored by Construct 2 - they are there for readability only.-->
    <name>e07_Game_farm</name>
    <events>
        <variable comment="dias que va completando la misión 1 = primer día" constant="0" name="consecutivoDia" sid="517144503279101" static="0" type="number">0</variable>
        <variable constant="1" name="cFinDia" sid="378310848182712" static="0" type="text">¡Felicidades! Has completado la misión del día </variable>
        <variable constant="0" name="status" sid="136760279146205" static="0" type="text">nulo</variable>
        <event-group description="" sid="390927723385015" title="mainChar">
            <sub-events>
                <event-block sid="599187265375872">
                    <conditions>
                        <condition id="4" name="Is touching object" sid="927035356298601" type="Touch">
                            <param id="0" name="Object">btnRight</param>
                        </condition>
                    </conditions>
                    <actions>
                        <action id="4" name="Set animation" sid="288741831042991" type="farmMainCharacter">
                            <param id="0" name="Animation">&quot;right&quot;</param>
                            <param id="1" name="From">1</param>
                        </action>
                        <action behavior="8Direction" id="7" name="Simulate control" sid="173470800865048" type="farmMainCharacter">
                            <param id="0" name="Control">1</param>
                        </action>
                    </actions>
                </event-block>
                <event-block sid="661110588566585">
                    <conditions>
                        <condition id="4" name="Is touching object" sid="190812997404855" type="Touch">
                            <param id="0" name="Object">btnLeft</param>
                        </condition>
                    </conditions>
                    <actions>
                        <action id="4" name="Set animation" sid="491487241502056" type="farmMainCharacter">
                            <param id="0" name="Animation">&quot;left&quot;</param>
                            <param id="1" name="From">1</param>
                        </action>
                        <action behavior="8Direction" id="7" name="Simulate control" sid="835297152793403" type="farmMainCharacter">
                            <param id="0" name="Control">0</param>
                        </action>
                    </actions>
                </event-block>
                <event-block sid="952493354103404">
                    <conditions>
                        <condition id="4" name="Is touching object" sid="909630551629113" type="Touch">
                            <param id="0" name="Object">btnUp</param>
                        </condition>
                    </conditions>
                    <actions>
                        <action id="4" name="Set animation" sid="436674194230499" type="farmMainCharacter">
                            <param id="0" name="Animation">&quot;up&quot;</param>
                            <param id="1" name="From">1</param>
                        </action>
                        <action behavior="8Direction" id="7" name="Simulate control" sid="145762729749954" type="farmMainCharacter">
                            <param id="0" name="Control">2</param>
                        </action>
                    </actions>
                </event-block>
                <event-block sid="120909149302080">
                    <conditions>
                        <condition id="4" name="Is touching object" sid="264116343502179" type="Touch">
                            <param id="0" name="Object">btnDown</param>
                        </condition>
                    </conditions>
                    <actions>
                        <action id="4" name="Set animation" sid="195674086703158" type="farmMainCharacter">
                            <param id="0" name="Animation">&quot;down&quot;</param>
                            <param id="1" name="From">1</param>
                        </action>
                        <action behavior="8Direction" id="7" name="Simulate control" sid="618124531819470" type="farmMainCharacter">
                            <param id="0" name="Control">3</param>
                        </action>
                    </actions>
                </event-block>
                <event-block sid="802119344703098">
                    <conditions>
                        <condition id="11" name="On Nth touch end" sid="416731214565548" type="Touch">
                            <param id="0" name="Touch number">0</param>
                        </condition>
                    </conditions>
                    <actions>
                        <action id="4" name="Set animation" sid="277518849412533" type="farmMainCharacter">
                            <param id="0" name="Animation">&quot;idle&quot;</param>
                            <param id="1" name="From">1</param>
                        </action>
                    </actions>
                </event-block>
            </sub-events>
        </event-group>
        <event-group description="" sid="572077063247005" title="Selecciones">
            <sub-events>
                <event-block sid="378776854775875">
                    <conditions>
                        <condition id="17" name="On tap object" sid="569878429444925" type="Touch">
                            <param id="0" name="Object">inv_axe</param>
                        </condition>
                        <condition id="-8" name="Is boolean instance variable set" sid="314648193040205" type="inv_axe">
                            <param id="0" name="Instance variable">activo</param>
                        </condition>
                        <condition id="-8" name="Is boolean instance variable set" sid="255357671782683" type="tree1">
                            <param id="0" name="Instance variable">colision</param>
                        </condition>
                    </conditions>
                    <actions>
                        <action id="-13" name="Set boolean" sid="735947302217847" type="inv_axe">
                            <param id="0" name="Instance variable">activo</param>
                            <param id="1" name="Value">0</param>
                        </action>
                        <action id="0" name="Call function" sid="644602375957232" type="Function">
                            <param id="0" name="Name">&quot;cerarModalInventario&quot;</param>
                            <param id="1" name="Parameter {n}"></param>
                        </action>
                        <action id="-16" name="Wait" sid="927623348961147" type="System">
                            <param id="0" name="Seconds">1</param>
                        </action>
                        <action id="0" name="Play" sid="249659508777249" type="Audio">
                            <param id="0" name="Audio file">corte</param>
                            <param id="2" name="Loop">0</param>
                            <param id="3" name="Volume">0</param>
                            <param id="1" name="Tag (optional)">&quot;corte&quot;</param>
                        </action>
                        <action id="0" name="Spawn another object" sid="287579207168537" type="tree1">
                            <param id="0" name="Object">particulas_blanco</param>
                            <param id="1" name="Layer">&quot;main&quot;</param>
                            <param id="2" name="Image point">0</param>
                        </action>
                        <action id="-9" name="Destroy" sid="432436964282951" type="tree1" />
                        <action id="-9" name="Destroy" sid="575343164167029" type="tree2" />
                        <action id="-16" name="Wait" sid="115061936030907" type="System">
                            <param id="0" name="Seconds">1</param>
                        </action>
                        <action id="0" name="Play" sid="767689645878036" type="Audio">
                            <param id="0" name="Audio file">logrado1</param>
                            <param id="2" name="Loop">0</param>
                            <param id="3" name="Volume">0</param>
                            <param id="1" name="Tag (optional)">&quot;corte&quot;</param>
                        </action>
                        <action id="-15" name="Set visible" sid="253997939964577" type="tablas_madera">
                            <param id="0" name="Visibility">1</param>
                        </action>
                        <action id="-13" name="Set boolean" sid="624621193438612" type="tablas_madera">
                            <param id="0" name="Instance variable">activo</param>
                            <param id="1" name="Value">1</param>
                        </action>
                        <action id="0" name="Spawn another object" sid="898517035235957" type="tablas_madera">
                            <param id="0" name="Object">particulas_rojo</param>
                            <param id="1" name="Layer">&quot;main&quot;</param>
                            <param id="2" name="Image point">0</param>
                        </action>
                    </actions>
                </event-block>
                <event-block sid="737611550526027">
                    <conditions>
                        <condition id="17" name="On tap object" sid="238127705820009" type="Touch">
                            <param id="0" name="Object">inv_semillas</param>
                        </condition>
                        <condition id="-8" name="Is boolean instance variable set" sid="912538629333897" type="inv_semillas">
                            <param id="0" name="Instance variable">activo</param>
                        </condition>
                        <condition id="-8" name="Is boolean instance variable set" sid="958929566258195" type="palita">
                            <param id="0" name="Instance variable">colision</param>
                        </condition>
                    </conditions>
                    <actions>
                        <action id="-13" name="Set boolean" sid="934060832602356" type="inv_semillas">
                            <param id="0" name="Instance variable">activo</param>
                            <param id="1" name="Value">0</param>
                        </action>
                        <action id="-9" name="Destroy" sid="665238574783225" type="palita" />
                        <action id="0" name="Call function" sid="458568479903713" type="Function">
                            <param id="0" name="Name">&quot;cerarModalInventario&quot;</param>
                            <param id="1" name="Parameter {n}"></param>
                        </action>
                        <action id="-16" name="Wait" sid="659177335423970" type="System">
                            <param id="0" name="Seconds">1.5</param>
                        </action>
                        <action id="0" name="Play" sid="973986165440324" type="Audio">
                            <param id="0" name="Audio file">logrado1</param>
                            <param id="2" name="Loop">0</param>
                            <param id="3" name="Volume">0</param>
                            <param id="1" name="Tag (optional)">&quot;logrado&quot;</param>
                        </action>
                        <action id="4" name="Set animation" sid="790875821725549" type="carriot">
                            <param id="0" name="Animation">&quot;semilla&quot;</param>
                            <param id="1" name="From">1</param>
                        </action>
                        <action id="-15" name="Set visible" sid="782967561894650" type="carriot">
                            <param id="0" name="Visibility">1</param>
                        </action>
                        <action id="-13" name="Set boolean" sid="628961480591309" type="carriot">
                            <param id="0" name="Instance variable">activo</param>
                            <param id="1" name="Value">1</param>
                        </action>
                        <action id="0" name="Call function" sid="973124523355336" type="Function">
                            <param id="0" name="Name">&quot;abrirPapiro&quot;</param>
                            <param id="1" name="Parameter {n}"></param>
                        </action>
                    </actions>
                </event-block>
                <event-block sid="207495070444908">
                    <conditions>
                        <condition id="17" name="On tap object" sid="857304954257125" type="Touch">
                            <param id="0" name="Object">inv_carretillo</param>
                        </condition>
                        <condition id="-8" name="Is boolean instance variable set" sid="221830865095692" type="inv_carretillo">
                            <param id="0" name="Instance variable">activo</param>
                        </condition>
                        <condition id="-8" name="Is boolean instance variable set" sid="992782361037138" type="arena">
                            <param id="0" name="Instance variable">colision</param>
                        </condition>
                    </conditions>
                    <actions>
                        <action id="-13" name="Set boolean" sid="705545166477983" type="inv_carretillo">
                            <param id="0" name="Instance variable">activo</param>
                            <param id="1" name="Value">0</param>
                        </action>
                        <action id="0" name="Call function" sid="337042819615018" type="Function">
                            <param id="0" name="Name">&quot;cerarModalInventario&quot;</param>
                            <param id="1" name="Parameter {n}"></param>
                        </action>
                        <action id="0" name="Play" sid="923961175449937" type="Audio">
                            <param id="0" name="Audio file">logrado1</param>
                            <param id="2" name="Loop">0</param>
                            <param id="3" name="Volume">0</param>
                            <param id="1" name="Tag (optional)">&quot;corte&quot;</param>
                        </action>
                        <action id="-3" name="Set position" sid="834369535193872" type="arena">
                            <param id="0" name="X">1632</param>
                            <param id="1" name="Y">64</param>
                        </action>
                        <action id="-13" name="Set boolean" sid="155290316776314" type="arena">
                            <param id="0" name="Instance variable">activo</param>
                            <param id="1" name="Value">1</param>
                        </action>
                    </actions>
                </event-block>
                <event-block sid="535316469867461">
                    <conditions>
                        <condition id="17" name="On tap object" sid="180899473715199" type="Touch">
                            <param id="0" name="Object">inv_regadera</param>
                        </condition>
                        <condition id="-8" name="Is boolean instance variable set" sid="171222265008725" type="inv_regadera">
                            <param id="0" name="Instance variable">activo</param>
                        </condition>
                        <condition id="-8" name="Is boolean instance variable set" sid="925567917712632" type="sensorHuerta">
                            <param id="0" name="Instance variable">colision</param>
                        </condition>
                        <condition id="-8" name="Is boolean instance variable set" sid="367549448062381" type="carriot">
                            <param id="0" name="Instance variable">activo</param>
                        </condition>
                    </conditions>
                    <actions>
                        <action id="-13" name="Set boolean" sid="540536997790293" type="inv_regadera">
                            <param id="0" name="Instance variable">activo</param>
                            <param id="1" name="Value">0</param>
                        </action>
                        <action id="0" name="Call function" sid="851981521293899" type="Function">
                            <param id="0" name="Name">&quot;cerarModalInventario&quot;</param>
                            <param id="1" name="Parameter {n}"></param>
                        </action>
                        <action id="0" name="Play" sid="779427383126438" type="Audio">
                            <param id="0" name="Audio file">logrado1</param>
                            <param id="2" name="Loop">0</param>
                            <param id="3" name="Volume">0</param>
                            <param id="1" name="Tag (optional)">&quot;corte&quot;</param>
                        </action>
                        <action id="4" name="Set animation" sid="843731922354187" type="carriot">
                            <param id="0" name="Animation">&quot;planta&quot;</param>
                            <param id="1" name="From">1</param>
                        </action>
                        <action id="-13" name="Set boolean" sid="345718555363555" type="sensorHuerta">
                            <param id="0" name="Instance variable">activo</param>
                            <param id="1" name="Value">1</param>
                        </action>
                        <action id="0" name="Call function" sid="611280268257753" type="Function">
                            <param id="0" name="Name">&quot;abrirPapiro2&quot;</param>
                            <param id="1" name="Parameter {n}"></param>
                        </action>
                    </actions>
                </event-block>
                <event-block sid="128283790913983">
                    <conditions>
                        <condition id="17" name="On tap object" sid="177469515438334" type="Touch">
                            <param id="0" name="Object">inv_heno</param>
                        </condition>
                        <condition id="-8" name="Is boolean instance variable set" sid="960852515199768" type="inv_heno">
                            <param id="0" name="Instance variable">activo</param>
                        </condition>
                        <condition id="-8" name="Is boolean instance variable set" sid="849870773411598" type="cow2">
                            <param id="0" name="Instance variable">colision</param>
                        </condition>
                    </conditions>
                    <actions>
                        <action id="-13" name="Set boolean" sid="953575445681961" type="inv_heno">
                            <param id="0" name="Instance variable">activo</param>
                            <param id="1" name="Value">0</param>
                        </action>
                        <action id="0" name="Call function" sid="271844777589787" type="Function">
                            <param id="0" name="Name">&quot;cerarModalInventario&quot;</param>
                            <param id="1" name="Parameter {n}"></param>
                        </action>
                        <action id="0" name="Play" sid="663919119682824" type="Audio">
                            <param id="0" name="Audio file">vaca</param>
                            <param id="2" name="Loop">0</param>
                            <param id="3" name="Volume">0</param>
                            <param id="1" name="Tag (optional)">&quot;vaca&quot;</param>
                        </action>
                        <action id="-13" name="Set boolean" sid="210906625734951" type="cow2">
                            <param id="0" name="Instance variable">activo</param>
                            <param id="1" name="Value">1</param>
                        </action>
                        <action id="0" name="Call function" sid="483499869634596" type="Function">
                            <param id="0" name="Name">&quot;abrirPapiro2&quot;</param>
                            <param id="1" name="Parameter {n}"></param>
                        </action>
                    </actions>
                </event-block>
                <comment>Construcción de la cabaña (casa - choza)</comment>
                <event-block sid="671652475834634">
                    <conditions>
                        <condition id="17" name="On tap object" sid="382512469212645" type="Touch">
                            <param id="0" name="Object">inv_hand</param>
                        </condition>
                        <condition id="-8" name="Is boolean instance variable set" sid="891528972271919" type="tablas_madera">
                            <param id="0" name="Instance variable">activo</param>
                        </condition>
                        <condition id="-8" name="Is boolean instance variable set" sid="816951448429334" type="ladrilloCasa">
                            <param id="0" name="Instance variable">activo</param>
                        </condition>
                        <condition id="-8" name="Is boolean instance variable set" sid="977667700214323" type="baseCasa">
                            <param id="0" name="Instance variable">colision</param>
                        </condition>
                    </conditions>
                    <actions>
                        <action id="-13" name="Set boolean" sid="389223797690207" type="inv_hand">
                            <param id="0" name="Instance variable">activo</param>
                            <param id="1" name="Value">0</param>
                        </action>
                        <action id="0" name="Call function" sid="447973627101920" type="Function">
                            <param id="0" name="Name">&quot;cerarModalInventario&quot;</param>
                            <param id="1" name="Parameter {n}"></param>
                        </action>
                        <action id="-3" name="Set position" sid="384993619145916" type="farmMainCharacter">
                            <param id="0" name="X">608</param>
                            <param id="1" name="Y">256</param>
                        </action>
                        <action id="0" name="Play" sid="744369320180095" type="Audio">
                            <param id="0" name="Audio file">logrado1</param>
                            <param id="2" name="Loop">0</param>
                            <param id="3" name="Volume">0</param>
                            <param id="1" name="Tag (optional)">&quot;corte&quot;</param>
                        </action>
                        <action id="-3" name="Set position" sid="113961119569518" type="choza">
                            <param id="0" name="X">832</param>
                            <param id="1" name="Y">117</param>
                        </action>
                        <action id="-15" name="Set visible" sid="875238743234374" type="choza">
                            <param id="0" name="Visibility">1</param>
                        </action>
                        <action id="-15" name="Set visible" sid="298277511751768" type="tablas_madera">
                            <param id="0" name="Visibility">0</param>
                        </action>
                        <action id="-15" name="Set visible" sid="795373128637848" type="ladrilloCasa">
                            <param id="0" name="Visibility">0</param>
                        </action>
                        <action id="-13" name="Set boolean" sid="252932214706794" type="choza">
                            <param id="0" name="Instance variable">activo</param>
                            <param id="1" name="Value">1</param>
                        </action>
                        <action id="-9" name="Set value" sid="207355653375475" type="System">
                            <param id="0" name="Variable">status</param>
                            <param id="1" name="Value">&quot;cabña construida&quot;</param>
                        </action>
                        <action id="0" name="Call function" sid="776843689574706" type="Function">
                            <param id="0" name="Name">&quot;abrirPapiro&quot;</param>
                            <param id="1" name="Parameter {n}"></param>
                        </action>
                    </actions>
                </event-block>
                <comment>Construcción del granero</comment>
                <event-block sid="433747736623392">
                    <conditions>
                        <condition id="17" name="On tap object" sid="887802083928376" type="Touch">
                            <param id="0" name="Object">inv_hand</param>
                        </condition>
                    </conditions>
                    <actions />
                    <sub-events>
                        <event-block sid="670388239769445">
                            <conditions>
                                <condition id="-8" name="Is boolean instance variable set" sid="833529281897187" type="baseGranero">
                                    <param id="0" name="Instance variable">colision</param>
                                </condition>
                                <condition id="-8" name="Is boolean instance variable set" sid="834949572257629" type="arena">
                                    <param id="0" name="Instance variable">activo</param>
                                </condition>
                                <condition id="-8" name="Is boolean instance variable set" sid="485905409263456" type="ladrilloGranero">
                                    <param id="0" name="Instance variable">activo</param>
                                </condition>
                                <condition id="-8" name="Is boolean instance variable set" sid="705385309493902" type="choza">
                                    <param id="0" name="Instance variable">activo</param>
                                </condition>
                            </conditions>
                            <actions>
                                <action id="0" name="Call function" sid="681700766725494" type="Function">
                                    <param id="0" name="Name">&quot;cerarModalInventario&quot;</param>
                                    <param id="1" name="Parameter {n}"></param>
                                </action>
                                <action id="-15" name="Set visible" sid="931944301719331" type="arena">
                                    <param id="0" name="Visibility">0</param>
                                </action>
                                <action id="0" name="Play" sid="945756076324048" type="Audio">
                                    <param id="0" name="Audio file">logrado1</param>
                                    <param id="2" name="Loop">0</param>
                                    <param id="3" name="Volume">0</param>
                                    <param id="1" name="Tag (optional)">&quot;corte&quot;</param>
                                </action>
                                <action id="-3" name="Set position" sid="417909881766822" type="granero">
                                    <param id="0" name="X">1792</param>
                                    <param id="1" name="Y">160</param>
                                </action>
                                <action id="-15" name="Set visible" sid="894426788059374" type="granero">
                                    <param id="0" name="Visibility">1</param>
                                </action>
                                <action id="-3" name="Set position" sid="962922483261984" type="farmMainCharacter">
                                    <param id="0" name="X">1792</param>
                                    <param id="1" name="Y">340</param>
                                </action>
                                <action id="-9" name="Set value" sid="400430145992674" type="System">
                                    <param id="0" name="Variable">status</param>
                                    <param id="1" name="Value">&quot;Granero construido&quot;</param>
                                </action>
                            </actions>
                        </event-block>
                    </sub-events>
                </event-block>
            </sub-events>
        </event-group>
        <event-group description="" sid="773044282847917" title="Colisiones">
            <sub-events>
                <event-block any="1" sid="704478060648402">
                    <conditions>
                        <condition id="0" name="On collision with another object" sid="565480135546420" type="farmMainCharacter">
                            <param id="0" name="Object">tree1</param>
                        </condition>
                    </conditions>
                    <actions>
                        <action id="-13" name="Set boolean" sid="355580387288718" type="tree1">
                            <param id="0" name="Instance variable">colision</param>
                            <param id="1" name="Value">1</param>
                        </action>
                        <action id="0" name="Call function" sid="107276297105229" type="Function">
                            <param id="0" name="Name">&quot;abrirModalInv&quot;</param>
                            <param id="1" name="Parameter {n}"></param>
                        </action>
                    </actions>
                </event-block>
                <event-block any="1" sid="227478175441345">
                    <conditions>
                        <condition id="0" name="On collision with another object" sid="970572796638644" type="farmMainCharacter">
                            <param id="0" name="Object">regadera</param>
                        </condition>
                    </conditions>
                    <actions>
                        <action id="-9" name="Destroy" sid="677355654611130" type="regadera" />
                        <action id="-13" name="Set boolean" sid="360896425921623" type="inv_regadera">
                            <param id="0" name="Instance variable">activo</param>
                            <param id="1" name="Value">1</param>
                        </action>
                        <action id="-15" name="Set visible" sid="201312480834405" type="inv_regadera">
                            <param id="0" name="Visibility">1</param>
                        </action>
                    </actions>
                </event-block>
                <event-block any="1" sid="752926648305320">
                    <conditions>
                        <condition id="0" name="On collision with another object" sid="609339428105414" type="farmMainCharacter">
                            <param id="0" name="Object">heno</param>
                        </condition>
                    </conditions>
                    <actions>
                        <action id="-9" name="Destroy" sid="322226907774933" type="heno" />
                        <action id="-13" name="Set boolean" sid="292716613444231" type="inv_heno">
                            <param id="0" name="Instance variable">activo</param>
                            <param id="1" name="Value">1</param>
                        </action>
                        <action id="-15" name="Set visible" sid="843831791787947" type="inv_heno">
                            <param id="0" name="Visibility">1</param>
                        </action>
                    </actions>
                </event-block>
                <event-block any="1" sid="398411437854321">
                    <conditions>
                        <condition id="0" name="On collision with another object" sid="458209170101093" type="farmMainCharacter">
                            <param id="0" name="Object">palita</param>
                        </condition>
                    </conditions>
                    <actions>
                        <action id="-13" name="Set boolean" sid="871225440212243" type="palita">
                            <param id="0" name="Instance variable">colision</param>
                            <param id="1" name="Value">1</param>
                        </action>
                        <action id="0" name="Call function" sid="898008889245742" type="Function">
                            <param id="0" name="Name">&quot;abrirModalInv&quot;</param>
                            <param id="1" name="Parameter {n}"></param>
                        </action>
                    </actions>
                </event-block>
                <event-block any="1" sid="835550516773034">
                    <conditions>
                        <condition id="0" name="On collision with another object" sid="149982312278977" type="farmMainCharacter">
                            <param id="0" name="Object">cow2</param>
                        </condition>
                    </conditions>
                    <actions>
                        <action id="-13" name="Set boolean" sid="473526385277133" type="cow2">
                            <param id="0" name="Instance variable">colision</param>
                            <param id="1" name="Value">1</param>
                        </action>
                        <action id="0" name="Call function" sid="668182519135533" type="Function">
                            <param id="0" name="Name">&quot;abrirModalInv&quot;</param>
                            <param id="1" name="Parameter {n}"></param>
                        </action>
                    </actions>
                </event-block>
                <event-block sid="807131861588179">
                    <conditions>
                        <condition id="0" name="On collision with another object" sid="543417444266446" type="farmMainCharacter">
                            <param id="0" name="Object">arena</param>
                        </condition>
                        <condition id="-8" name="Is boolean instance variable set" sid="743327048363004" type="inv_carretillo">
                            <param id="0" name="Instance variable">activo</param>
                        </condition>
                    </conditions>
                    <actions>
                        <action id="-13" name="Set boolean" sid="208285181166805" type="arena">
                            <param id="0" name="Instance variable">colision</param>
                            <param id="1" name="Value">1</param>
                        </action>
                        <action id="0" name="Call function" sid="668499686935473" type="Function">
                            <param id="0" name="Name">&quot;abrirModalInv&quot;</param>
                            <param id="1" name="Parameter {n}"></param>
                        </action>
                    </actions>
                </event-block>
                <event-block any="1" sid="720608550666010">
                    <conditions>
                        <condition id="0" name="On collision with another object" sid="656576488481707" type="farmMainCharacter">
                            <param id="0" name="Object">hacha</param>
                        </condition>
                    </conditions>
                    <actions>
                        <action id="-9" name="Destroy" sid="522566440614960" type="hacha" />
                        <action id="-15" name="Set visible" sid="626426927271997" type="inv_axe">
                            <param id="0" name="Visibility">1</param>
                        </action>
                        <action id="-13" name="Set boolean" sid="931169451553293" type="inv_axe">
                            <param id="0" name="Instance variable">activo</param>
                            <param id="1" name="Value">1</param>
                        </action>
                        <action id="0" name="Play" sid="590544073651193" type="Audio">
                            <param id="0" name="Audio file">obtenido</param>
                            <param id="2" name="Loop">0</param>
                            <param id="3" name="Volume">0</param>
                            <param id="1" name="Tag (optional)">&quot;obtenido&quot;</param>
                        </action>
                    </actions>
                </event-block>
                <event-block any="1" sid="948434670828912">
                    <conditions>
                        <condition id="0" name="On collision with another object" sid="422616557970516" type="farmMainCharacter">
                            <param id="0" name="Object">carretillo</param>
                        </condition>
                    </conditions>
                    <actions>
                        <action id="-9" name="Destroy" sid="716363190833912" type="carretillo" />
                        <action id="-15" name="Set visible" sid="484922093299465" type="inv_carretillo">
                            <param id="0" name="Visibility">1</param>
                        </action>
                        <action id="-13" name="Set boolean" sid="395949107437068" type="inv_carretillo">
                            <param id="0" name="Instance variable">activo</param>
                            <param id="1" name="Value">1</param>
                        </action>
                        <action id="0" name="Play" sid="363882883226533" type="Audio">
                            <param id="0" name="Audio file">obtenido</param>
                            <param id="2" name="Loop">0</param>
                            <param id="3" name="Volume">0</param>
                            <param id="1" name="Tag (optional)">&quot;obtenido&quot;</param>
                        </action>
                    </actions>
                </event-block>
                <event-block any="1" sid="790517516933579">
                    <conditions>
                        <condition id="0" name="On collision with another object" sid="452489450071106" type="farmMainCharacter">
                            <param id="0" name="Object">semillas</param>
                        </condition>
                    </conditions>
                    <actions>
                        <action id="-9" name="Destroy" sid="397466177302439" type="semillas" />
                        <action id="-15" name="Set visible" sid="247437411084205" type="inv_semillas">
                            <param id="0" name="Visibility">1</param>
                        </action>
                        <action id="-13" name="Set boolean" sid="964701963505123" type="inv_semillas">
                            <param id="0" name="Instance variable">activo</param>
                            <param id="1" name="Value">1</param>
                        </action>
                        <action id="0" name="Play" sid="484227741778843" type="Audio">
                            <param id="0" name="Audio file">obtenido</param>
                            <param id="2" name="Loop">0</param>
                            <param id="3" name="Volume">0</param>
                            <param id="1" name="Tag (optional)">&quot;obtenido&quot;</param>
                        </action>
                    </actions>
                </event-block>
                <event-block any="1" sid="664546784175465">
                    <conditions>
                        <condition id="0" name="On collision with another object" sid="619481005470775" type="farmMainCharacter">
                            <param id="0" name="Object">ladrilloGranero</param>
                        </condition>
                    </conditions>
                    <actions>
                        <action id="-16" name="Wait" sid="915369268480526" type="System">
                            <param id="0" name="Seconds">0.5</param>
                        </action>
                        <action id="0" name="Play" sid="479976351377767" type="Audio">
                            <param id="0" name="Audio file">logrado1</param>
                            <param id="2" name="Loop">0</param>
                            <param id="3" name="Volume">0</param>
                            <param id="1" name="Tag (optional)">&quot;logrado&quot;</param>
                        </action>
                        <action id="-3" name="Set position" sid="268186864838220" type="ladrilloGranero">
                            <param id="0" name="X">1760</param>
                            <param id="1" name="Y">96</param>
                        </action>
                        <action id="-13" name="Set boolean" sid="617950627939283" type="ladrilloGranero">
                            <param id="0" name="Instance variable">activo</param>
                            <param id="1" name="Value">1</param>
                        </action>
                        <action id="-13" name="Set boolean" sid="793746917687412" type="ladrilloGranero">
                            <param id="0" name="Instance variable">colision</param>
                            <param id="1" name="Value">1</param>
                        </action>
                    </actions>
                </event-block>
                <event-block any="1" sid="355923269582106">
                    <conditions>
                        <condition id="0" name="On collision with another object" sid="412780805521548" type="farmMainCharacter">
                            <param id="0" name="Object">ladrilloCasa</param>
                        </condition>
                    </conditions>
                    <actions>
                        <action id="-16" name="Wait" sid="438751941048903" type="System">
                            <param id="0" name="Seconds">0.5</param>
                        </action>
                        <action id="0" name="Play" sid="721123841267097" type="Audio">
                            <param id="0" name="Audio file">logrado1</param>
                            <param id="2" name="Loop">0</param>
                            <param id="3" name="Volume">0</param>
                            <param id="1" name="Tag (optional)">&quot;logrado&quot;</param>
                        </action>
                        <action id="-3" name="Set position" sid="565019541762960" type="ladrilloCasa">
                            <param id="0" name="X">877</param>
                            <param id="1" name="Y">82</param>
                        </action>
                        <action id="-13" name="Set boolean" sid="649860348560742" type="ladrilloCasa">
                            <param id="0" name="Instance variable">activo</param>
                            <param id="1" name="Value">1</param>
                        </action>
                        <action id="-13" name="Set boolean" sid="766565565006977" type="ladrilloCasa">
                            <param id="0" name="Instance variable">colision</param>
                            <param id="1" name="Value">1</param>
                        </action>
                    </actions>
                </event-block>
                <event-block sid="596551923152657">
                    <conditions>
                        <condition id="0" name="On collision with another object" sid="901231227802175" type="farmMainCharacter">
                            <param id="0" name="Object">baseCasa</param>
                        </condition>
                    </conditions>
                    <actions>
                        <action id="0" name="Call function" sid="387160045979852" type="Function">
                            <param id="0" name="Name">&quot;abrirModalInv&quot;</param>
                            <param id="1" name="Parameter {n}"></param>
                        </action>
                        <action id="-13" name="Set boolean" sid="862804673557439" type="baseCasa">
                            <param id="0" name="Instance variable">colision</param>
                            <param id="1" name="Value">1</param>
                        </action>
                    </actions>
                </event-block>
                <event-block sid="803989238269526">
                    <conditions>
                        <condition id="0" name="On collision with another object" sid="967682051872654" type="farmMainCharacter">
                            <param id="0" name="Object">baseGranero</param>
                        </condition>
                    </conditions>
                    <actions>
                        <action id="0" name="Call function" sid="823238379425377" type="Function">
                            <param id="0" name="Name">&quot;abrirModalInv&quot;</param>
                            <param id="1" name="Parameter {n}"></param>
                        </action>
                        <action id="-13" name="Set boolean" sid="789910442489632" type="baseGranero">
                            <param id="0" name="Instance variable">colision</param>
                            <param id="1" name="Value">1</param>
                        </action>
                    </actions>
                </event-block>
                <event-block sid="132425847987467">
                    <conditions>
                        <condition id="0" name="On collision with another object" sid="469858610817933" type="farmMainCharacter">
                            <param id="0" name="Object">sensorHuerta</param>
                        </condition>
                    </conditions>
                    <actions>
                        <action id="0" name="Call function" sid="615211424115472" type="Function">
                            <param id="0" name="Name">&quot;abrirModalInv&quot;</param>
                            <param id="1" name="Parameter {n}"></param>
                        </action>
                        <action id="-13" name="Set boolean" sid="459401952971582" type="sensorHuerta">
                            <param id="0" name="Instance variable">colision</param>
                            <param id="1" name="Value">1</param>
                        </action>
                    </actions>
                </event-block>
            </sub-events>
        </event-group>
        <event-group description="" sid="625679334791743" title="Eventos_generales">
            <sub-events>
                <event-block sid="640459346368774">
                    <conditions>
                        <condition id="17" name="On tap object" sid="700763587779189" type="Touch">
                            <param id="0" name="Object">btnClose</param>
                        </condition>
                    </conditions>
                    <actions>
                        <action id="0" name="Call function" sid="548754494383767" type="Function">
                            <param id="0" name="Name">&quot;cerarModalInventario&quot;</param>
                            <param id="1" name="Parameter {n}"></param>
                        </action>
                    </actions>
                </event-block>
                <event-block sid="965404332513554">
                    <conditions>
                        <condition id="17" name="On tap object" sid="164047575765172" type="Touch">
                            <param id="0" name="Object">btnInventario</param>
                        </condition>
                    </conditions>
                    <actions>
                        <action id="0" name="Call function" sid="651570589566266" type="Function">
                            <param id="0" name="Name">&quot;abrirModalInv&quot;</param>
                            <param id="1" name="Parameter {n}"></param>
                        </action>
                    </actions>
                </event-block>
            </sub-events>
        </event-group>
        <event-group description="" sid="236474492639731" title="Funciones">
            <sub-events>
                <event-block sid="170452937815649">
                    <conditions>
                        <condition id="0" name="On function" sid="330354436679134" type="Function">
                            <param id="0" name="Name">&quot;cerarModalInventario&quot;</param>
                        </condition>
                    </conditions>
                    <actions>
                        <action id="-4" name="Set layer visible" sid="105622023561118" type="System">
                            <param id="0" name="Layer">&quot;modal_inv&quot;</param>
                            <param id="1" name="Visibility">0</param>
                        </action>
                        <action id="-4" name="Set layer visible" sid="550455573952739" type="System">
                            <param id="0" name="Layer">&quot;shadow&quot;</param>
                            <param id="1" name="Visibility">0</param>
                        </action>
                        <action id="-13" name="Set boolean" sid="962557594404515" type="tree1">
                            <param id="0" name="Instance variable">colision</param>
                            <param id="1" name="Value">0</param>
                        </action>
                        <action id="-13" name="Set boolean" sid="112544322355119" type="arena">
                            <param id="0" name="Instance variable">colision</param>
                            <param id="1" name="Value">0</param>
                        </action>
                        <action id="-13" name="Set boolean" sid="438119945740133" type="ladrilloGranero">
                            <param id="0" name="Instance variable">colision</param>
                            <param id="1" name="Value">0</param>
                        </action>
                        <action id="-13" name="Set boolean" sid="485283525654961" type="ladrilloCasa">
                            <param id="0" name="Instance variable">colision</param>
                            <param id="1" name="Value">0</param>
                        </action>
                        <action id="-13" name="Set boolean" sid="777336375791657" type="palita">
                            <param id="0" name="Instance variable">colision</param>
                            <param id="1" name="Value">0</param>
                        </action>
                        <action id="-16" name="Wait" sid="105851859525057" type="System">
                            <param id="0" name="Seconds">1</param>
                        </action>
                        <action id="-13" name="Set boolean" sid="502811763202971" type="baseCasa">
                            <param id="0" name="Instance variable">colision</param>
                            <param id="1" name="Value">0</param>
                        </action>
                        <action id="-13" name="Set boolean" sid="123136216374918" type="sensorHuerta">
                            <param id="0" name="Instance variable">colision</param>
                            <param id="1" name="Value">0</param>
                        </action>
                    </actions>
                </event-block>
                <event-block sid="662096407878054">
                    <conditions>
                        <condition id="0" name="On function" sid="621762195664748" type="Function">
                            <param id="0" name="Name">&quot;abrirPapiro&quot;</param>
                        </condition>
                        <condition id="-8" name="Is boolean instance variable set" sid="539326230152592" type="choza">
                            <param id="0" name="Instance variable">activo</param>
                        </condition>
                        <condition id="-8" name="Is boolean instance variable set" sid="940454153871181" type="carriot">
                            <param id="0" name="Instance variable">activo</param>
                        </condition>
                    </conditions>
                    <actions>
                        <action id="-9" name="Set value" sid="320185484185264" type="System">
                            <param id="0" name="Variable">status</param>
                            <param id="1" name="Value">&quot;fin dia 1&quot;</param>
                        </action>
                        <action id="-16" name="Wait" sid="764293698008964" type="System">
                            <param id="0" name="Seconds">3</param>
                        </action>
                        <action id="6" name="Stop" sid="903009088513995" type="Audio">
                            <param id="0" name="Tag">&quot;ambiente&quot;</param>
                        </action>
                        <action id="-9" name="Set value" sid="809864917103703" type="System">
                            <param id="0" name="Variable">status</param>
                            <param id="1" name="Value">&quot;Mostrando papiro dia 1&quot;</param>
                        </action>
                        <action id="-9" name="Set value" sid="835190405362969" type="System">
                            <param id="0" name="Variable">consecutivoDia</param>
                            <param id="1" name="Value">consecutivoDia + 1</param>
                        </action>
                        <action id="0" name="Set text" sid="742010760857355" type="txtfinDia">
                            <param id="0" name="Text">CFINDIA &amp;  &quot; &quot;  &amp; consecutivoDia</param>
                        </action>
                        <action id="0" name="Play" sid="290004245946345" type="Audio">
                            <param id="0" name="Audio file">Finish1</param>
                            <param id="2" name="Loop">0</param>
                            <param id="3" name="Volume">0</param>
                            <param id="1" name="Tag (optional)">&quot;&quot;</param>
                        </action>
                        <action id="-4" name="Set layer visible" sid="367837464242725" type="System">
                            <param id="0" name="Layer">&quot;modal_papiro&quot;</param>
                            <param id="1" name="Visibility">1</param>
                        </action>
                        <action id="-4" name="Set layer visible" sid="378377950310300" type="System">
                            <param id="0" name="Layer">&quot;shadow&quot;</param>
                            <param id="1" name="Visibility">1</param>
                        </action>
                        <action id="-16" name="Wait" sid="824469259001426" type="System">
                            <param id="0" name="Seconds">5</param>
                        </action>
                        <action id="-4" name="Set layer visible" sid="470513287920965" type="System">
                            <param id="0" name="Layer">&quot;modal_papiro&quot;</param>
                            <param id="1" name="Visibility">0</param>
                        </action>
                        <action id="-4" name="Set layer visible" sid="220100242237656" type="System">
                            <param id="0" name="Layer">&quot;shadow&quot;</param>
                            <param id="1" name="Visibility">0</param>
                        </action>
                        <action id="-9" name="Set value" sid="830548155527258" type="System">
                            <param id="0" name="Variable">status</param>
                            <param id="1" name="Value">&quot;Ocultando  papiro dia 1&quot;</param>
                        </action>
                        <action id="0" name="Play" sid="903156611890546" type="Audio">
                            <param id="0" name="Audio file">timescapes</param>
                            <param id="2" name="Loop">1</param>
                            <param id="3" name="Volume">0</param>
                            <param id="1" name="Tag (optional)">&quot;ambiente2&quot;</param>
                        </action>
                    </actions>
                </event-block>
                <event-block sid="783396978904959">
                    <conditions>
                        <condition id="0" name="On function" sid="604234150398808" type="Function">
                            <param id="0" name="Name">&quot;abrirPapiro2&quot;</param>
                        </condition>
                        <condition id="-8" name="Is boolean instance variable set" sid="617112130487481" type="sensorHuerta">
                            <param id="0" name="Instance variable">activo</param>
                        </condition>
                        <condition id="-8" name="Is boolean instance variable set" sid="118848171172641" type="cow2">
                            <param id="0" name="Instance variable">activo</param>
                        </condition>
                    </conditions>
                    <actions>
                        <action id="-9" name="Set value" sid="886088986079856" type="System">
                            <param id="0" name="Variable">status</param>
                            <param id="1" name="Value">&quot;fin dia 2&quot;</param>
                        </action>
                        <action id="-16" name="Wait" sid="534263660054099" type="System">
                            <param id="0" name="Seconds">3</param>
                        </action>
                        <action id="6" name="Stop" sid="449836093221730" type="Audio">
                            <param id="0" name="Tag">&quot;ambiente2&quot;</param>
                        </action>
                        <action id="-9" name="Set value" sid="850386809436755" type="System">
                            <param id="0" name="Variable">status</param>
                            <param id="1" name="Value">&quot;Mostrando papiro dia 2&quot;</param>
                        </action>
                        <action id="-9" name="Set value" sid="454215624605988" type="System">
                            <param id="0" name="Variable">consecutivoDia</param>
                            <param id="1" name="Value">consecutivoDia + 1</param>
                        </action>
                        <action id="0" name="Set text" sid="412484078852724" type="txtfinDia">
                            <param id="0" name="Text">CFINDIA &amp;  &quot; &quot;  &amp; consecutivoDia</param>
                        </action>
                        <action id="0" name="Play" sid="607176130798209" type="Audio">
                            <param id="0" name="Audio file">Finish1</param>
                            <param id="2" name="Loop">0</param>
                            <param id="3" name="Volume">0</param>
                            <param id="1" name="Tag (optional)">&quot;&quot;</param>
                        </action>
                        <action id="-4" name="Set layer visible" sid="787602977180769" type="System">
                            <param id="0" name="Layer">&quot;modal_papiro&quot;</param>
                            <param id="1" name="Visibility">1</param>
                        </action>
                        <action id="-4" name="Set layer visible" sid="267104318644668" type="System">
                            <param id="0" name="Layer">&quot;shadow&quot;</param>
                            <param id="1" name="Visibility">1</param>
                        </action>
                        <action id="-16" name="Wait" sid="492570452401823" type="System">
                            <param id="0" name="Seconds">5</param>
                        </action>
                        <action id="-4" name="Set layer visible" sid="710891182325095" type="System">
                            <param id="0" name="Layer">&quot;modal_papiro&quot;</param>
                            <param id="1" name="Visibility">0</param>
                        </action>
                        <action id="-4" name="Set layer visible" sid="474301697086612" type="System">
                            <param id="0" name="Layer">&quot;shadow&quot;</param>
                            <param id="1" name="Visibility">0</param>
                        </action>
                        <action id="-9" name="Set value" sid="579348906111394" type="System">
                            <param id="0" name="Variable">status</param>
                            <param id="1" name="Value">&quot;Ocultando  papiro dia 2&quot;</param>
                        </action>
                        <action id="0" name="Play" sid="881073736251690" type="Audio">
                            <param id="0" name="Audio file">amazonas</param>
                            <param id="2" name="Loop">1</param>
                            <param id="3" name="Volume">0</param>
                            <param id="1" name="Tag (optional)">&quot;ambiente&quot;</param>
                        </action>
                    </actions>
                </event-block>
                <event-block sid="105018574947013">
                    <conditions>
                        <condition id="0" name="On function" sid="235525991429688" type="Function">
                            <param id="0" name="Name">&quot;abrirModalInv&quot;</param>
                        </condition>
                    </conditions>
                    <actions>
                        <action id="-9" name="Set value" sid="285866413506924" type="System">
                            <param id="0" name="Variable">status</param>
                            <param id="1" name="Value">&quot;Abriendo modal&quot;</param>
                        </action>
                        <action id="-4" name="Set layer visible" sid="537373741519311" type="System">
                            <param id="0" name="Layer">&quot;shadow&quot;</param>
                            <param id="1" name="Visibility">1</param>
                        </action>
                        <action id="-4" name="Set layer visible" sid="295497861700049" type="System">
                            <param id="0" name="Layer">&quot;modal_inv&quot;</param>
                            <param id="1" name="Visibility">1</param>
                        </action>
                    </actions>
                </event-block>
            </sub-events>
        </event-group>
        <event-group description="" sid="288392222517428" title="OnLoad">
            <sub-events>
                <event-block sid="279006828555637">
                    <conditions>
                        <condition id="-25" name="On loader layout complete" sid="703592176193939" type="System" />
                    </conditions>
                    <actions>
                        <action id="-9" name="Set value" sid="240941407476784" type="System">
                            <param id="0" name="Variable">status</param>
                            <param id="1" name="Value">&quot;loaded&quot;</param>
                        </action>
                    </actions>
                </event-block>
            </sub-events>
        </event-group>
    </events>
</c2eventsheet>
